{
    "$schema": "http://json-schema.org/draft-04/schema#",
    "type": "object",
    "properties": {
        "id": {
            "type": "string"
        },
        "title": {
            "type": [
                "string",
                "null"
            ]
        },
        "description": {
            "type": [
                "string",
                "null"
            ]
        },
        "priority": {
            "type": "number"
        },
        "url": {
            "type": "string"
        },
        "state": {
            "type": "object",
            "properties": {
                "id": {
                    "type": "string"
                },
                "name": {
                    "type": "string"
                }
            }
        },
        "history": {
            "type": "array",
            "items": {
                "type": "object",
                "properties": {
                    "actor": {
                        "type": "object",
                        "properties": {
                            "id": {
                                "type": "string"
                            }
                        }
                    },
                    "createdAt": {
                        "type": [
                            "string",
                            "null"
                        ]
                    },
                    "fromState": {
                        "type": [
                            "string",
                            "null"
                        ]
                    },
                    "toState": {
                        "type": [
                            "string",
                            "null"
                        ]
                    }
                }
            }
        },
        "startedAt": {
            "type": "string"
        },
        "parent": {
            "type": "object",
            "properties": {
                "id": {
                    "type": "string"
                }
            }
        },
        "assignee": {
            "type": "object",
            "properties": {
                "id": {
                    "type": "string"
                },
                "name": {
                    "type": "string"
                },
                "createdAt": {
                    "type": "string"
                }
            }
        },
        "createdAt": {
            "type": "string"
        },
        "updatedAt": {
            "type": "string"
        },
        "labels": {
            "type": "array",
            "items": {
                "type": "object",
                "properties": {
                    "id": {
                        "type": "string"
                    },
                    "name": {
                        "type": "string"
                    }
                }
            }
        },
        "project": {
            "type": "object",
            "properties": {
                "id": {
                    "type": "string"
                },
                "name": {
                    "type": "string"
                }
            }
        },
        "cycle": {
            "type": "object",
            "properties": {
                "id": {
                    "type": "string"
                }
            }
        },
        "creator": {
            "type": "object",
            "properties": {
                "id": {
                    "type": "string"
                }
            }
        }
    }
}
