{
  "title": "SquadCast",
  "description": "Configuration options that apply to records generated by the SquadCast Source.",
  "type": "object",
  "oneOf": [
    {
      "type": "object",
      "title": "Configuration",
      "properties": {
        "application_mapping": {
          "type": "string",
          "title": "Application Mapping",
          "description": "JSON map of SquadCast service(s) name, to compute platform specific app name and platform name. Used to reference compute_Application object, from an ims_Incident object.",
          "multiline": true,
          "default": "{}",
          "examples": [
            "{ \"Aion\": { \"name\": \"aion\", \"platform\": \"ECS\" } }"
          ]
        }
      }
    }
  ]
}
